CHANGES.txt
MANIFEST.in
README.rst
setup.py
tox.ini
pyramid_jwtauth/__init__.py
pyramid_jwtauth/utils.py
pyramid_jwtauth.egg-info/PKG-INFO
pyramid_jwtauth.egg-info/SOURCES.txt
pyramid_jwtauth.egg-info/dependency_links.txt
pyramid_jwtauth.egg-info/not-zip-safe
pyramid_jwtauth.egg-info/requires.txt
pyramid_jwtauth.egg-info/top_level.txt
pyramid_jwtauth/tests/__init__.py
pyramid_jwtauth/tests/test_jwtauth.py
pyramid_jwtauth/tests/test_utils.py