Metadata-Version: 1.1
Name: pyramid-jwtauth
Version: 0.1.3
Summary: pyramid_jwtauth
Home-page: https://github.com/ajkavanagh/pyramid_jwtauth
Author: Alex Kavanagh (Websand)
Author-email: alex@ajkavanagh.co.uk
License: MPLv2.0
Keywords: authentication token JWT JSON
Platform: UNKNOWN
Classifier: Development Status :: 4 - Beta
Classifier: Framework :: Pyramid
Classifier: Intended Audience :: Developers
Classifier: Topic :: Internet :: WWW/HTTP
Classifier: Programming Language :: Python :: 2
Classifier: Programming Language :: Python :: 2.7
Classifier: Programming Language :: Python :: 3
Classifier: Programming Language :: Python :: 3.3
Classifier: Programming Language :: Python :: 3.4
Classifier: License :: OSI Approved :: Mozilla Public License 2.0 (MPL 2.0)
